MANIFEST.in
README.txt
setup.py
Project_Grid_lock.egg-info/PKG-INFO
Project_Grid_lock.egg-info/SOURCES.txt
Project_Grid_lock.egg-info/dependency_links.txt
Project_Grid_lock.egg-info/requires.txt
Project_Grid_lock.egg-info/top_level.txt
gridlock/__init__.py