Metadata-Version: 1.0
Name: Project-Grid-lock
Version: 1.0
Summary: A module that allows the use of positions in images as a password
Home-page: UNKNOWN
Author: Shanyu Dabbiru, Pranav Reddy Dumpa
Author-email: project.gridlock.2022@gmail.com
License: MIT
Platform: UNKNOWN
